gmatautomation/__init__.py
gmatautomation/modelcontrol/__init__.py
gmatautomation/modelcontrol/gmat_batcher.py
gmatautomation/modelgen/__init__.py
gmatautomation/modelgen/fromconfigsheet.py
gmatautomation/modelgen/gmatlocator.py
gmatautomation/modelgen/modelgen.py
gmatautomation/modelgen/modelpov.py
gmatautomation/reportgen/CleanUpData.py
gmatautomation/reportgen/CleanUpReports.py
gmatautomation/reportgen/ContactReports.py
gmatautomation/reportgen/LinkReports.py
gmatautomation/reportgen/__init__.py
gmatautomation/reportgen/reduce_report.py
gmatautomation-0.3b3.dist-info/LICENSE
gmatautomation-0.3b3.dist-info/METADATA
gmatautomation-0.3b3.dist-info/WHEEL
gmatautomation-0.3b3.dist-info/top_level.txt
gmatautomation-0.3b3.dist-info/RECORD
