Metadata-Version: 2.1
Name: gmatautomation
Version: 0.3b3
Summary: GMAT model generation, batch execution, and data reduction.
Home-page: https://github.com/a093130/GMAT-Automation
Author: Colin Helms
Author-email: colinhelms@outlook.com
Project-URL: Bug Tracker, https://github.com/users/a093130/projects/2
Classifier: Development Status :: 4 - Beta
Classifier: Environment :: Console
Classifier: Environment :: Plugins
Classifier: Intended Audience :: Science/Research
Classifier: Operating System :: Microsoft :: Windows :: Windows 10
Classifier: Programming Language :: Python :: 3.7
Classifier: License :: OSI Approved :: GNU General Public License v3 (GPLv3)
Classifier: Topic :: Scientific/Engineering :: Mathematics
Requires-Python: >=3.4
License-File: LICENSE
